hacksaws/__init__.py
hacksaws/_aws.py
hacksaws/_cli.py
hacksaws/_configs.py
hacksaws/_ecr.py
hacksaws-0.3.0.dist-info/METADATA
hacksaws-0.3.0.dist-info/WHEEL
hacksaws-0.3.0.dist-info/entry_points.txt
hacksaws-0.3.0.dist-info/RECORD
