Metadata-Version: 2.3
Name: hacksaws
Version: 0.3.0
Summary: A command line utility for AWS profiles using dynamic authentication methods such as MFA. 
License: MIT
Keywords: aws,authentication
Author: Scott Ernst
Author-email: swernst@gmail.com
Requires-Python: >=3.10.3,<4.0.0
Classifier: Development Status :: 4 - Beta
Classifier: Environment :: Console
Classifier: Intended Audience :: Developers
Classifier: License :: OSI Approved :: MIT License
Classifier: Programming Language :: Python :: 3
Classifier: Programming Language :: Python :: 3.11
Classifier: Programming Language :: Python :: 3.12
Classifier: Programming Language :: Python :: 3.13
Classifier: Programming Language :: Python :: 3.10
Classifier: Topic :: Utilities
Requires-Dist: boto3 (>=1.16.0,<2.0.0)
Project-URL: Documentation, https://gitlab.com/rocket-boosters/hacksaws
Project-URL: Homepage, https://gitlab.com/rocket-boosters/hacksaws
Project-URL: Repository, https://gitlab.com/rocket-boosters/hacksaws
